setup.py
timeit.py
micropython_timeit.egg-info/PKG-INFO
micropython_timeit.egg-info/SOURCES.txt
micropython_timeit.egg-info/dependency_links.txt
micropython_timeit.egg-info/requires.txt
micropython_timeit.egg-info/top_level.txt