Metadata-Version: 1.0
Name: micropython-timeit
Version: 3.3.3-2
Summary: CPython timeit module ported to MicroPython
Home-page: https://github.com/micropython/micropython/issues/405
Author: MicroPython Developers
Author-email: micro-python@googlegroups.com
License: Python
Platform: UNKNOWN
